README.rst
pyproject.toml
setup.py
botl/__init__.py
botl/__main__.py
botl/cache.py
botl/client.py
botl/disk.py
botl/error.py
botl/event.py
botl/find.py
botl/fleet.py
botl/object.py
botl/reactor.py
botl/thread.py
botl/timer.py
botl/utils.py
botl/workdir.py
botl.egg-info/PKG-INFO
botl.egg-info/SOURCES.txt
botl.egg-info/dependency_links.txt
botl.egg-info/entry_points.txt
botl.egg-info/top_level.txt
botl/modules/__init__.py
botl/modules/dbg.py
botl/modules/err.py
botl/modules/flt.py
botl/modules/fnd.py
botl/modules/irc.py
botl/modules/llm.py
botl/modules/log.py
botl/modules/man.py
botl/modules/mbx.py
botl/modules/mdl.py
botl/modules/mod.py
botl/modules/req.py
botl/modules/rss.py
botl/modules/rst.py
botl/modules/slg.py
botl/modules/tbl.py
botl/modules/tdo.py
botl/modules/thr.py
botl/modules/tmr.py
botl/modules/udp.py
botl/modules/upt.py
botl/modules/web.py
botl/modules/wsd.py