Metadata-Version: 2.1
Name: botl
Version: 130
Summary: bot library
Author-email: Bart Thate <bthate@dds.nl>
License: Public Domain
Project-URL: home, https://pypi.org/project/botl
Project-URL: bugs, https://github.com/otpcr/botl/issues
Project-URL: source, https://github.com/otpcr/botl
Classifier: Development Status :: 4 - Beta
Classifier: License :: Public Domain
Classifier: Operating System :: Unix
Classifier: Programming Language :: Python :: 3
Classifier: Topic :: Utilities
